dynamic_sound/__init__.py
dynamic_sound/_simulation.py
dynamic_sound/_version.py
dynamic_sound/acoustics/__init__.py
dynamic_sound/acoustics/attenuations.py
dynamic_sound/acoustics/doppler.py
dynamic_sound/acoustics/standards/ISO_9613_1_1993.py
dynamic_sound/acoustics/standards/__init__.py
dynamic_sound/acoustics/utils.py
dynamic_sound/environment/__init__.py
dynamic_sound/environment/_air.py
dynamic_sound/environment/_path.py
dynamic_sound/microphones/__init__.py
dynamic_sound/microphones/_hedraphone.py
dynamic_sound/microphones/_microphones.py
dynamic_sound/py.typed
dynamic_sound/sources/__init__.py
dynamic_sound/sources/_audio_file.py
dynamic_sound/sources/_sine_wave.py
dynamic_sound/sources/_source.py
dynamic_sound/sources/_white_noise.py
dynamic_sound-1.0.2.dist-info/WHEEL
dynamic_sound-1.0.2.dist-info/METADATA
dynamic_sound-1.0.2.dist-info/RECORD
