Metadata-Version: 2.3
Name: dynamic-sound
Version: 1.0.2
Summary: Add your description here
Author: Luca Barbisan
Author-email: Luca Barbisan <luca.barbisan@polito.it>
License:                                  Apache License
Requires-Dist: librosa>=0.11.0
Requires-Dist: matplotlib>=3.10.6
Requires-Dist: numpy>=2.2.6
Requires-Dist: numpy-quaternion>=2024.0.12
Requires-Dist: scipy>=1.15.3
Requires-Dist: tqdm>=4.67.1
Requires-Python: >=3.10
